aurorae/__init__.py
aurorae/__main__.py
aurorae/cnab240/__init__.py
aurorae/cnab240/base.py
aurorae/cnab240/v10_7/__init__.py
aurorae/cnab240/v10_7/lambdas.py
aurorae/cnab240/v10_7/models.py
aurorae/cnab240/v10_7/types.py
aurorae/cnab240/writer.py
aurorae/payroll/__init__.py
aurorae/payroll/models.py
aurorae/providers/__init__.py
aurorae/providers/api/main.py
aurorae/providers/exceptions.py
aurorae/providers/spreadsheet/__init__.py
aurorae/providers/spreadsheet/handler.py
aurorae/providers/spreadsheet/models.py
aurorae/providers/spreadsheet/utils.py
aurorae/providers/spreadsheet/validators.py
aurorae/providers/utils.py
aurorae/sample/aurorae-cnab240-sample-file.html
aurorae/sample/aurorae-cnab240-sample-file.txt
aurorae/sample/spreadsheet_sample.xlsx
aurorae/staticfiles/styles.css
aurorae-0.0.2.dist-info/entry_points.txt
aurorae-0.0.2.dist-info/LICENSE.txt
aurorae-0.0.2.dist-info/WHEEL
aurorae-0.0.2.dist-info/METADATA
aurorae-0.0.2.dist-info/RECORD
