Metadata-Version: 2.1
Name: aurorae
Version: 0.0.2
Summary: A Python implementation of the CNAB240 file to perform bulk payments.
License: MIT
Keywords: cnab240,payments,openbanking
Author: Mariane Pastor (Vinta Software)
Author-email: mariane.pastor@vinta.com.br
Requires-Python: >=3.7,<4.0
Classifier: Development Status :: 2 - Pre-Alpha
Classifier: Intended Audience :: Developers
Classifier: License :: OSI Approved :: MIT License
Classifier: Natural Language :: English
Classifier: Programming Language :: Python :: 3
Classifier: Programming Language :: Python :: 3.7
Classifier: Programming Language :: Python :: 3.8
Classifier: Programming Language :: Python :: 3.9
Classifier: Topic :: Office/Business :: Financial :: Accounting
Classifier: Topic :: Office/Business :: Financial :: Spreadsheet
Provides-Extra: docs
Requires-Dist: Pygments (>=2.9.0,<3.0.0)
Requires-Dist: attrs (>=21.2.0,<22.0.0)
Requires-Dist: backcall (>=0.2.0,<0.3.0)
Requires-Dist: decorator (>=5.0.9,<6.0.0)
Requires-Dist: et-xmlfile (>=1.1.0,<2.0.0)
Requires-Dist: fastapi (>=0.68.0,<0.69.0)
Requires-Dist: iniconfig (>=1.1.1,<2.0.0)
Requires-Dist: ipython (>=7.25.0,<8.0.0)
Requires-Dist: ipython_genutils (>=0.2.0,<0.3.0)
Requires-Dist: jedi (>=0.18.0,<0.19.0)
Requires-Dist: openpyxl (>=3.0.7,<4.0.0)
Requires-Dist: packaging (>=21.0,<22.0)
Requires-Dist: parso (>=0.8.2,<0.9.0)
Requires-Dist: pexpect (>=4.8.0,<5.0.0)
Requires-Dist: pickleshare (>=0.7.5,<0.8.0)
Requires-Dist: pluggy (>=0.13.1,<0.14.0)
Requires-Dist: prompt-toolkit (>=3.0.19,<4.0.0)
Requires-Dist: ptyprocess (>=0.7.0,<0.8.0)
Requires-Dist: py (>=1.10.0,<2.0.0)
Requires-Dist: pydantic (>=1.8.2,<2.0.0)
Requires-Dist: pyparsing (>=2.4.7,<3.0.0)
Requires-Dist: requests (>=2.26.0,<3.0.0)
Requires-Dist: toml (>=0.10.2,<0.11.0)
Requires-Dist: traitlets (>=5.0.5,<6.0.0)
Requires-Dist: uvicorn[standard] (>=0.15.0,<0.16.0)
Requires-Dist: wcwidth (>=0.2.5,<0.3.0)
